[
  {
    "filename": "Truck Consignment Delivery Note.pdf",
    "path": "docs/Truck Consignment Delivery Note.pdf",
    "status": "data_extracted",
    "doc_type": "goods_receipt_note",
    "extracted_text_content": "OgLSeey $9 126+ W \u201cYebeUS - OTT COEBTE | |_| SRNR dd abi sora nom SSaudxX3 IANA TA EN (ones | Wisi 5 TIGAVM NUsalSsaM |\n\n\u00a30000LLLP9SE00L #NUL UVHOS 8 woo 1EqnpjJeA MMM \u2018qpanoexyqor f= sCtti\u201c\u2018CS\u00e9C;C;O*\u2122!;*;C~S\u2122 ai ped ~~\" :foUSUIND) TWLOL 2 Lad =\" UOHEISANY / [OL PEOY / 824 \u201cO'C / SSI. merererere=s\"\"* \u201cSOUBIBSID) SLUO}SND ao'o cossceeneenernetneeetentseesneeeeenenneeneeeeete et DIOG BAH | IPNBS | CBS yseg ; x sereerreeeseeerereeeeeeesee @BuBUS) BUEN / UOHISdSUY LWA 4 oes oie \u201cAng swioysn9 ISSEq 8]2D \u201c:yoeweunoog nO / aBseyD Od / snogeT uy 0} Joud eouesNsU! ofJe 40) UaAI6 eGueyD 1yS!e14 S1VL30 39YVHD ewiL 2 120 :WeN ory sAped Pau junosoy eeuBjsuog qunossy seddiys SUV130 LNSWAVd awl gy ayeq aimeubis s,eeubisuog Jeaieno pajulid suoNIpuos pue SWJe} SNOILONUYLSNI WWI93dS NOlLdiddS3G W3LI sauoydajay SI 19IH3A JO \u2018ON SdAL STOIHSA \"yw eigesbieyo q WM S819 SYM \u201ceWNjOA, ; SOWUNJOA [BIOL \u2018SNOISNAWIG :sebeyoed JO \u2018ON 48A1898y) J3NDISNOD 626 \u00a3286 996+ 'CETCG SPZ 896+ UL JEUOS B IEOSNW \u2018seyoUEIG Bled Ssaudxg WeIseMm\n\nES IM\n\nYaddiHsS\n\n4\n\nSs\n\nsAqunog\n\nseuoydeal\n\n\u201c@JON JusWUBISUOD S14) JO s,ssaudx3 wajseny ay) eesBy 8/I\n\nYK\n\naueN ainjeubig sseddiys\n\n\u2018AG GaL0aT109 \"yuewidiys jo yoyedsap aq 0} SUORONsISU! Je!NadS :2]0N\n\nVON YONAL\n\nAG G3YSAN3G \u2018OWEN $,18N0D\n\nSON ONL,\n\n|\n\n| |\n\n{ } |\n\n28WEN S,JaNoD\n\nIVOSNIN 'HYPYVHS \u2018SSHONVES\n\n2 Leminar \u2014~ GLOBAL \u2014\u2014 Commitment Beyond Comparison\n\nLeminar Air Conditioning Company LLC (..a.3) Guu Si Lik TS pnd Dubai P.O. Box 33539, Tel- Off: +971 4 333 8700; Showrooms: +971 4 223 6910/ +971 4 250 4423 324 1850 Abu Dhabi : P.O. Box 34523, Tel- Off: +971 25510228 /+971 2 621 4149; Showroom: +971 2677 1065 AlAin P.O. Box 98927, Tel - Oif: +971 3 754 9387; Showroom: +971 3 722 4036; Fujairah: Tel - Showroom: +971 9 234 1336 Sharjah: Tel - Off: +971 6 525 8837; Showroom: +971 6 532 4280; Ras Al Khaimah: Tel- Showroom: +971 72337965 a : i Email: info@leminar.ae; Website: www.leminarnet; Paid up Capital AED 1,200,000; CR No.45046\n\n~ | 3 IR 1SO 9001\n\nCOMMERCIAL INVOICE CUM PACKING LIST\n\nDATE OF EXPORT |__Invoice Date [Invoice# | CURRENCY 8/14/2023 8/11/2023 LACO-39\n\nSHIPPER / EXPORTER Leminar Air- Conditioning Co LLC Dubai PO BOX 33539\n\nCONSIGNEE\n\nUNIT VALUE FJFF 65, FJFF 300, FJFF 75 }40169990] India | 470.00 156.56 [a faseevanes \u2018Yass! can [soso] a7 [aoa Clamp and Accessories . 2.70 i Ce <1 867,626736, 625593, 625675, 625678, 625399, TOTAL VALUE m 16,249.26 6,107.18 16,438.44 5,532.64 > iv) > m 0 w N \u00b0 N S oo a 7,695.34 D) Total Weight - 1522 KG Total AED In Words- Fifty Two Thousand Twenty Two & 86/100 Dirhams Only. Total AED 52,022.86\n\n\n\n3k\n\nMEP Supplier of the year 2022, O19, 2018, 2016 & 2012 >& HVAC Accessories Provider of the year 2021, 2019, 2017, 2016, 2015, 2013 & 2012\n\n\n\nRee y\n\nDY SP\n\nTE] frese CMA ate \u2014 Carmacell = TESS (UNO murtten EMERSON\n\nee \u2014E\u2014 INIERS INIER _), Nerit inousTRiaL KIMMMCO ISOVer BNADE NAPCO 7? W s @ GENERAL pumps ofe sover ZURN NAPCO iE sieumes fOtS\n\n\u201csy CORT, Z GOVERNMENT OF DUBAI\n\ngaeljloa Dubai Customs\n\n= =,\n\nat Joes / C99 > bali ged CUSTOMS EXIT / ENTRY CERTIFICATE\n\nExporter | LEMINAR AIR CONDITIONING CO LLC saat Date| 25 08 | 2023 | 15 [15 08 | 2023 | svt T Export bill 5 ae 3 Slay! ert Air Hide bill Bill no. hull ad, Date dab 203-04144376-23 15 08 2023 Country of origin Latta Point of exit Earddl Ss Destination sued! aby\n\ndsaSI! Quantity\n\nDescription of goods\n\nFolia! arog Aplucll SiLtg5l Cpe Lgiags pec\u2019 pall Se Ail Le Lal cine 9p do Description of goods must enable identification on original documents Rubber Support\n\npity\n\n= gig SII Bgl Website : www.dubaicustoms.gov.ae\n\n\u00bb g\n\nz @ E = 5 \u00a9\n\n|\n\n> \u00a9 \u00a9\n\n03-PLT Spring Hanger FJFF 65, FJFF 300, FJFF 75 Hattersley Valves Clamp and Accessories INVOICE NO: LACO-39 Date : 11.08.2023 7 quantity aSJ1 weight Vin Lill od) / Ayla! ad) Alea! Wolo; 63) Container no. / Vehicle no. Customs seal no. 19817 DXB seca! ob ol Ugh! gl cg pS dled ys UyLeodl Gotu Customs certification at point of exit or country of destination Total! 93-pit glee lta 1522 KGS Ree wBodlels yySulldcLadl gb wets 3m be LALD (ye Sled! une limes | eee ae We certify that me It is certified that the above For Dubai Customs qe Uber Ye \u00a9 ena mentioned goods have been Dat x tl cleared by Customs. ate | | Sad the exporter needs this Sime Fad CG Il al gll 3a anlgacatl zis ele ger ee which proof that these goods have tie hates 13598 atl del P.O.Bua: 35.38, DUBAI- LAE. left the United Arab Emirates or poleder cts Rec citer! aro arrived in a foreign country so that gS dg coll ty oH Lg tpg gl S4caall! s the deposit paid may be refunded vet? Aybas Maas (ll qualill 208 suas Stamp by Dubai Customs ST ae eee : ASUS) 25 YI te Salgttt onde sfse! ow esas si lgule spel] 2 Y Zalgddl oe pccas This certificate must be prepared in typescript Any alteration will invalidate this certificate\n\n} |\n\n}\n\n|\n\n1\n\nUNITED ARAB EMIRATES Federal Customs Authority Sandal An jal) ol Lay) A ybaall 4ylacy) Agi Page1of1 DUBAI CUSTOMS | (tl | Il All| (II ont dylaa Handling Authorit [PORT TYPE jin gid C TYPE cla \u20ac 353] [DEC DATE ct @ G2) [DEC NO. LAND EXPORT 15/08/2023 203-04 144376-23 Customs Declaration Export Statistical Declaration 191002673234 (See Oly NET WEIGHT ital Gis) 7] [CONSIGNEE/EXPORTER sHaall/sjsiuad 6] [DELIVERY ORDER NO. agladll ou a5 AE-1011839 - LEMINAR AIR CONDITIONING CO LLC (1 - L0237) |GROSS WEIGHT ati) 45s 10] [INTERCESSOR CO. Apa sl 45,23 9] [CAR/CAPT. GL ea/AG 8 1522 (kg) MEASUREMENT uli) 13] [COMMERCIAL REG. NO. g ASD dant 43,12] [CARRIER'S NAME <a 1 226140 / EXPORTER VAT TRN: 100060237300003 NO. OF PACKAGES yh ue 16] [EXPORT TO 4a] staal 15] [ VOYAGE/FLIGHT NO. 4) ay 14] 3- PALLET MARKS & NUMBERS AGN! y cloud 19] [PORT OF LOADING \u201cGaede 18] [B/L \u201cAWB NO /MANIFEST Colin / Realy a8) 17| 19817 DXB, C.NOTE . 319303 DUBAI LAND TERMINAL PORT OF DISCHARGE did oie 20 DESTINATION sala! Aya 21 OMAN asus giles! 31] \u00a2 530) 4829], 4a) 28[CURRENCY lal a5] ah 24 Rela) ciay 23 Wau) ay 22 TOTAL DUTY | DN) | awl Myloal Alay [eon 27 gil 26] Gua Adeety | Catan GOODS DESCRIPTION H.S. CODE INCOME | DUTY ICIF LOCAL VALUE] RaTE [TYPE |CIF FOREIGN VALUE|ORIGIN AO ph a RATE {| AED aa \u2014_| | 0.00 0.0 7695.34 1.0000 | AED | 7695.34 IN CLAMP AND ACCESSORIES 82057000 i 0.00 0.0 16438.44 1.0000 | AED | 16438.44 IN FJFF 65, FJFF 300, FJF 40169990 0.00 0.0 6107.18 1.0000 | AED | 6107.18 IN SPRING HANGER 40169990 t 0.00 0.0 5532.64 1.0000 | AED | 5532.64 CN | HATTERSLEY VALVES 84818090 3 0.00 0.0 16249.26 1.0000 | AED | 16249.26 IN RUBBER SUPPORT 40169990 \u00b0 B} c | ab _t a. * SS 3 SS eS Se Se Se 7 CS SE So et ee a EXEMPTION OF DUTY Cisliey!) | WEIGHT CUsIICLASSFICATION Winall] PACKAGES 45 3] | [customs RESTRICTIONS \u2014 44 jaa) yal sited 44] puad 43] 42/1 \u00ab37 Lad 36a 33] GT Sle 33] Gam 33] Gail gam 41 BENEFICIARY SOURCES cove |1| GRoss NET unit | ty. | Type Qvy. |1| RELEASE REF \u2014 f 7 \u2014 er cS 41} 1 1522 kg | kg 1522 PLT 3 ' i ! ! i] f ' 1 I ! 1 t I i 1 ' 1 \u2018oc == SJ AED pa \u00bb[DUTY ag~oi]! [CLEARING AGENT cheat Galial 38] I[INSPECTION Aula 45 [TOTAL DUTY spat aya 56]! AE-1089633 IREASONS FOR NOT RELEASING Gail ae Guo]\n\nL\n\nHANDLING AJL aye 57] | WESTERN EXPRESS FREIGHT L.L.C 1 STORAGE Gina Wi py 58], [LICENCE No. Res 0 5,39] | OTHER CHARGES GA ayy 59/1 686545 DEFINITE | 75 P24 60] op plesll! INSURED ou 61\\TotaL Fee |\u201c PAYMENT METHOD aia 4448 62] [TRANSIT GURANTEE/CHEQUE Aye [gas 63 i ROUTE No. RGCH 50.00 [7517305] CA-1013047 4 64 KDID 20.00 [7517306] CA-1013047 ARCH 5.00 [7517304] CA-1013047\n\nfiz\n\n1\n\niz = >= SS SSSI a) INSPECTOR\n\n=\n\n=\n\n=\n\n== =\n\nEee) veal &3 50] [GROUP SUPERVISOR jens OTHER REMARKS\n\nEXIT PORT\n\nHATTA (AL WAJAJAH) EXIT TRANSACTION NO.\n\nEAI Spee 51]\n\nTs 48 52\n\n| [CIF] FRT: INS: Total Value: 52022.86\n\nCrane 46) fe $y ost 4715 i oA! CUaadte 48 :\n\nDATE\n\nBANK\n\nRECEIPT NO.\n\nDATE\n\nBANK\n\n&.4 65) [DATE 44 66| |SECURITY OFFICER ada Jun! oi) 67 &. 68] [TRANSIT OFFICER ay 69\n\nOistnbution | I~ Handling Authonty 2- Consignee 3- Consignee 4 Customs\n\n446 53 Gel Gy. 54]\n\nL ey 5 3 Gals 55] [RELEASE DATE 15/08/2023 westernfreight999 Aaah ajgheall \u201cPt a is\n\nTend) AE 49)",
    "extracted_tables_html": [
      "<pre>DATE OF EXPORT |__Invoice Date [Invoice# | CURRENCY 8/14/2023 8/11/2023 LACO-39</pre>",
      "<table><thead><tr><th>SR No</th><th>F SEN FI ES OPGGSDS</th><th>HS C boat</th><th>[onsin</th><th>WEIGHT [May |</th><th>TY oY |</th><th>UNIT VALUE | AED</th><th>TOTAL VALUE AED</th></tr></thead><tbody><tr><td>ry</td><td>Rubber Support</td><td>40169990 |</td><td>india |</td><td>552.00</td><td>29733</td><td>0.55</td><td>16,249.26</td></tr><tr><td>N</td><td>Spring Hanger</td><td>40169990</td><td></td><td>77.00</td><td></td><td>22.05</td><td>6,107.18</td></tr><tr><td>3</td><td>|FJFF 65, FJFF 300, FJFF 75</td><td>40169990 |</td><td>india. |</td><td>470.00</td><td></td><td>156.56</td><td>16,438.44</td></tr><tr><td>4</td><td>|Hattersley Valves</td><td>#4818090</td><td>China |</td><td>198.00</td><td></td><td>204.91</td><td>5,532.64</td></tr><tr><td>5</td><td>{Clamp and Accessories .</td><td>22057000]</td><td>India Inca |</td><td>225.00</td><td></td><td>2.70</td><td>7,695.34</td></tr><tr><td></td><td>)UB-TOTAL</td><td></td><td></td><td></td><td></td><td></td><td>AED</td></tr><tr><td></td><td></td><td></td><td></td><td></td><td></td><td>a</td><td>52,022.86</td></tr><tr><td colspan=\"8\">&lt;1 AC Ref. No. 627074, 626345, 626646, 627004,626867,626736, 625593, 625675, 625678, 625399, an Leeds aol 27689, 627188, 627190, 627196, 627199, 627223</td></tr><tr><td>\u2018otal otal otal</td><td>Weight - 1522 KG AED In Words- Fifty Two Thousand Twenty Packages ty ta</td><td>Two &amp; 86/100</td><td>Dirhams Only.</td><td></td><td></td><td>Total</td><td>AED 52,022.86</td></tr></tbody></table>",
      "<table><thead><tr><th></th><th colspan=\"2\" rowspan=\"2\">dikes \u00a2 9 4] [DEC TYPE EXPORT</th><th></th><th colspan=\"3\">call g 553) [DEC</th><th colspan=\"3\">DATE cu &amp;4G 2] [DEC NO.</th><th></th></tr></thead><tbody><tr><td rowspan=\"3\">[PORT TYPE LAND Customs Declaration</td><td colspan=\"4\">Authority mee pee srens</td><td colspan=\"4\">MMM</td><td colspan=\"3\">A ybaall 4ylacy) Agi 5 Pe</td></tr><tr><td colspan=\"3\" rowspan=\"2\">Export ital Gis) 7]</td><td></td><td></td><td></td><td></td><td colspan=\"3\">15/08/2023 203-04 144376-23</td><td></td></tr><tr><td>NET WEIGHT</td><td>Statistical [CONSIGNEE/EXPORTER</td><td>Declaration</td><td colspan=\"4\">sHaall/sjsiuad</td><td>191002673234 6] [DELIVERY ORDER</td><td>(ee OL NO. agladll</td></tr><tr><td>GROSS WEIGHT</td><td></td><td colspan=\"2\">AE-1011839 al Gis) 10] JINTERCESSOR</td><td colspan=\"4\">- LEMINAR AIR CONDITIONING CO CO.</td><td colspan=\"2\">LLC (1 - L0237) Apa sl</td><td>45,23 9] [CAR/CAPT.</td><td>ou a5</td></tr><tr><td>1522 (kg) MEXSURERENT</td><td></td><td>ui)</td><td>13) [COMMERCIAL</td><td colspan=\"2\">REG. NO.</td><td colspan=\"2\"></td><td colspan=\"3\" rowspan=\"2\">ges) dau of 12] [CARRIER'S NAME 42) jae) 15]</td><td>G/N aa</td></tr><tr><td>NO. OF PACKAGES</td><td></td><td>ay sh) we</td><td>226140 / 16] [EXPORT TO</td><td colspan=\"3\">EXPORTER VAT TRN:</td><td>100060237300003</td><td>aT</td></tr><tr><td rowspan=\"5\">3 - PALLET MARKS &amp; NUMBERS 19817 DXB , C.NOTE</td><td colspan=\"3\" rowspan=\"2\">aay) y cloud 19]</td><td></td><td></td><td colspan=\"2\" rowspan=\"2\"></td><td rowspan=\"2\"></td><td colspan=\"2\" rowspan=\"4\">| VOYAGE/FLIGHT 18] ]6/L -AWB NO./MANIFEST 20</td><td>NO. dis a</td></tr><tr><td>[PORT OF</td><td>LOADING</td><td></td></tr><tr><td>.</td><td colspan=\"2\" rowspan=\"3\">319303</td><td>DUBAI</td><td>LAND</td><td colspan=\"2\" rowspan=\"2\">Gall TERMINAL &amp;</td><td>\u00a2lie</td><td>Conlin / Aaa gal ah)</td></tr><tr><td></td><td>PORT OF</td><td>DISCHARGE</td><td>oi) 6.</td><td></td></tr><tr><td></td><td>DESTINATION OMAN</td><td colspan=\"3\" rowspan=\"2\">Aba aa 25] tual) ALeelL,</td><td>sala! Aya</td><td>21</td><td></td><td></td></tr><tr><td>agus plea! 31] TOTAL DUTY |</td><td>5130] aby!</td><td colspan=\"2\">4329] aw) Ayla Abel,</td><td>4,@)_28[CURRENCY [Aon 27</td><td>24</td><td colspan=\"2\">ictal diay 23 GOODS</td><td>Wat a 22</td></tr><tr><td>AO ph 0.00 0.00 0.00 0.00 0.00</td><td>INCOME | a</td><td>DUTY RATE {| 0.0 0.0 0.0 0.0 0.0</td><td>ICIF LOCAL VALUE] AED aa 7695.34 16438.44 6107.18 5532.64 16249.26</td><td>RaTE 1.0000 1.0000 1.0000 1.0000 1.0000</td><td>il 26] [TYPE |CIF | AED | | AED | | AED | | AED | | AED |</td><td colspan=\"2\" rowspan=\"2\">FOREIGN VALUE|ORIGIN 7695.34 16438.44 6107.18 5532.64 16249.26</td><td>Cain \u2014_| IN IN IN CN IN</td><td colspan=\"2\">DESCRIPTION CLAMP AND ACCESSORIES FJFF 65, FJFF 300, FF SPRING HANGER HATTERSLEY VALVES RUBBER SUPPORT</td><td>H.S. CODE 82057000 40169990 40169990 84818090 40169990</td></tr><tr><td>_ nee eee XEMPTION OF DUTY</td><td>oe ee</td><td>4 eos</td><td>\u201c</td><td>|</td><td></td><td></td><td colspan=\"2\">ro----------___u</td><td>a.</td></tr><tr><td>sited 44]</td><td>puad</td><td>43]</td><td>Sleliey!) | WEIGHT 42/1</td><td></td><td></td><td>CUsIICLASSFICATION 36a</td><td>Winall]</td><td>PACKAGES</td><td>35 5] 33]</td><td>[customs RESTRICTIONS</td><td>= aa ayaa)</td></tr><tr><td>BENEFICIARY 7</td><td>SOURCES</td><td></td><td>CODE |1| GRoss 1 \u2018 1 ! 1 ' ! t</td><td>\u00ab37 iP</td><td>Lad NET 1522kg]</td><td>33] unit | i kg |</td><td>GT Sle Qty. | TA 1522</td><td>33] TYPE PLT |</td><td>Gam QTY. |1| 3 i ' i} ! | 1</td><td>Gail gam 41 RELEASE REF th</td><td></td></tr><tr><td></td><td></td><td></td><td>1 ' 1 l= &gt;5</td><td></td><td></td><td></td><td></td><td>Ie</td><td>\\ | | | oe]</td><td></td><td></td></tr><tr><td>\\ED Ey</td><td>DUTY</td><td>4S</td><td>al! sl</td><td>CLEARING</td><td>AGENT</td><td></td><td>cee)</td><td>Valial</td><td>38] 1]</td><td>INSPECTION</td><td>Aula 45</td></tr></tbody></table>"
    ],
    "extracted_data": {
      "goods_receipt_note": {
        "document_id": "LACO-39",
        "export_date": "2023-08-14",
        "invoice_date": "2023-08-11",
        "shipper": {
          "name": "Leminar Air Conditioning Co LLC",
          "address": {
            "street": "P.O. Box 33539",
            "city": "Dubai",
            "country": "United Arab Emirates",
            "contact": {
              "phone": "+971 4 333 8700",
              "showrooms": [
                "+971 4 223 6910",
                "+971 4 250 4423"
              ]
            }
          }
        },
        "consignee": {
          "country": "India"
        },
        "line_items": [
          {
            "description": "Rubber Support",
            "hs_code": "40169990",
            "origin": "India",
            "weight": 552.0,
            "unit_value_aed": 29733,
            "total_value_aed": 16249.26
          },
          {
            "description": "Spring Hanger",
            "hs_code": "40169990",
            "weight": 77.0,
            "unit_value_aed": 22.05,
            "total_value_aed": 6107.18
          },
          {
            "description": "FJFF 65, FJFF 300, FJFF 75",
            "hs_code": "40169990",
            "origin": "India",
            "weight": 470.0,
            "unit_value_aed": 156.56,
            "total_value_aed": 16438.44
          },
          {
            "description": "Hattersley Valves",
            "hs_code": "84818090",
            "origin": "China",
            "weight": 198.0,
            "unit_value_aed": 204.91,
            "total_value_aed": 5532.64
          },
          {
            "description": "Clamp and Accessories",
            "hs_code": "22057000",
            "origin": "India",
            "weight": 225.0,
            "unit_value_aed": 2.7,
            "total_value_aed": 7695.34
          }
        ],
        "total_weight_kg": 1522,
        "total_value_aed": 52022.86,
        "total_value_in_words": "Fifty Two Thousand Twenty Two & 86/100 Dirhams Only",
        "customs_declaration": {
          "declaration_number": "203-04 144376-23",
          "declaration_date": "2023-08-15",
          "exporter_vat_trn": "100060237300003",
          "port_of_loading": "Dubai Land Terminal",
          "destination": "Oman"
        }
      }
    },
    "error_message": null
  },
  {
    "filename": "AI Engineer Challenge Invoice.PDF",
    "path": "docs/AI Engineer Challenge Invoice.PDF",
    "status": "data_extracted",
    "doc_type": "invoice",
    "extracted_text_content": "Tax Invoice\n\nTax Registration Number : 100060237300003\n\nCustomer No\n\n:\n\n128659\n\nInvoice No\n\n:\n\n626867-ADS1-1\n\nCustomer Name\n\n: LEMINAR AIR CONDITIONING CO. LLC\n\nInvoice Date\n\n:\n\n12-Aug-2023\n\n(Oman)\n\nSO No\n\n:\n\nSO-153412\n\nBill To Address\n\nCustomer Tax Reg No\n\nPhone\n\nFax\n\nContact Person\n\n:\n\n:\n\n:\n\n:\n\n:\n\nP.O. Box :946,\n\nRuwi,\n\nOman\n\nDue Date\n\nPO No\n\nSales Man\n\nDelivery Note No\n\nCurrency\n\nExchange Rate\n\n:\n\n10-Dec-2023\n\n:\n\n1002475\n\n: BHAVYA RAKESH\n\n:\n\n626867-ADS1-1\n\n: AED\n\n1\n\n:\n\nDot\n\nProject Name\n\n:\n\nINTERCOMPANY\n\nSr Item Code & Description Quantity UOM Unit Price Total Amount VAT VAT No (Excluding VAT) Rate(%) Amount 1 WEICCO Rubber Support Insert 25mm, 35.00 SET 4.82 168.70 0.00 0.00 RSI 3\" X 25mm (Width-38mm) Total Amount (Including VAT) 168.70\n\nTotal Amount (Excluding VAT)\n\n:\n\nVAT Amount : : AED One Hundred Sixty Eight and 70/100 Only. Total Amount (Including VAT) : : LPO - 120 Days Ship to Address : P.O. Box :946, : Ruwi, : Oman : : : : Receivers Name : Receivers Sign & Date : : Ofelia Authorized By :\n\nTotal Amount in Words\n\nPayment Terms\n\nBank Details\n\nBank Name\n\nBranch Name\n\nAccount Number\n\nIBAN\n\nSwift Code\n\nOther Terms and\n\nConditions\n\nPrepared By\n\n168.70\n\n0.00\n\n168.70\n\nPage | of 1",
    "extracted_tables_html": [
      "<table><tbody><tr><td>No 1 WEICCO Rubber Support Insert</td><td>25mm,</td><td>35.00</td><td>SET</td><td>4.82</td><td>(Excluding VAT) _ 168.70</td><td>0.00</td><td>Amount 0.00</td><td>(Including VAT) 168.70</td></tr></tbody></table>",
      "<table><thead><tr><th rowspan=\"2\">otal Amount in Words Payment Terms</th><th rowspan=\"2\">: :</th><th rowspan=\"2\">AED One Hundred Sixty Eight and 70/100 Only. LPO- 120 Days</th><th colspan=\"3\">Total Amount (Including VAT):</th><th>168.7</th></tr><tr><th></th><th></th><th></th><th></th></tr></thead><tbody><tr><td>Bank Details</td><td></td><td></td><td>Ship to Address</td><td>P.O.</td><td>Box :946,</td><td></td></tr><tr><td>Bank Name</td><td>:</td><td></td><td></td><td>Ruwi,</td><td></td><td></td></tr><tr><td>Branch Name</td><td>:</td><td></td><td></td><td>Oman</td><td></td><td></td></tr><tr><td>Account Number</td><td></td><td></td><td></td><td></td><td></td><td></td></tr><tr><td>[BAN</td><td></td><td></td><td></td><td></td><td></td><td></td></tr><tr><td>Swift Code</td><td></td><td></td><td></td><td></td><td></td><td></td></tr><tr><td>Other Terms and</td><td></td><td></td><td></td><td></td><td></td><td></td></tr><tr><td rowspan=\"3\">Conditions Prepared By</td><td></td><td></td><td>Receivers Name</td><td></td><td></td><td></td></tr><tr><td></td><td></td><td>Receivers Sign &amp; Date</td><td></td><td></td><td></td></tr><tr><td>:</td><td>Ofelia</td><td>Authorized By</td><td></td><td></td><td></td></tr></tbody></table>"
    ],
    "extracted_data": {
      "invoice": {
        "invoice_id": "626867-ADS1-1",
        "invoice_date": "2023-08-12",
        "due_date": "2023-12-10",
        "customer_number": "128659",
        "customer_name": "LEMINAR AIR CONDITIONING CO. LLC",
        "customer_tax_registration_number": "100060237300003",
        "bill_to_address": {
          "po_box": "946",
          "city": "Ruwi",
          "country": "Oman"
        },
        "sales_man": "BHAVYA RAKESH",
        "purchase_order_number": "1002475",
        "delivery_note_number": "626867-ADS1-1",
        "currency": "AED",
        "exchange_rate": 1,
        "project_name": "INTERCOMPANY",
        "line_items": [
          {
            "item_code": "WEICCO Rubber Support Insert",
            "description": "25mm",
            "quantity": 35,
            "uom": "SET",
            "unit_price": 4.82,
            "total_amount_excluding_vat": 168.7,
            "vat_amount": 0.0,
            "total_amount_including_vat": 168.7
          }
        ],
        "total_amount_excluding_vat": 168.7,
        "vat_amount": 0.0,
        "total_amount_including_vat": 168.7,
        "total_amount_in_words": "AED One Hundred Sixty Eight and 70/100 Only.",
        "payment_terms": "LPO - 120 Days",
        "bank_details": {
          "bank_name": "",
          "branch_name": "",
          "account_number": "",
          "iban": "",
          "swift_code": ""
        },
        "ship_to_address": {
          "po_box": "946",
          "city": "Ruwi",
          "country": "Oman"
        },
        "receiver_name": "Ofelia",
        "authorized_by": ""
      }
    },
    "error_message": null
  }
]